vinset/__init__.py
vinset/arial.ttf
vinset/calibri.ttf
vinset/helvetica.ttf
vinset/times.ttf
vinset/verdana.ttf
vinset/vinset.py
vinset-5.2.0.dist-info/LICENSE
vinset-5.2.0.dist-info/METADATA
vinset-5.2.0.dist-info/WHEEL
vinset-5.2.0.dist-info/entry_points.txt
vinset-5.2.0.dist-info/top_level.txt
vinset-5.2.0.dist-info/RECORD
