Metadata-Version: 2.1
Name: vinset
Version: 5.2.0
Summary: Command line program to draw the graph from video and csv files.
Author-email: Zaw Lin Tun <zawlintun1511@gmail.com>
Project-URL: Homepage, https://github.com/jtur044/vinset
Project-URL: Bug Tracker, https://github.com/jtur044/vinset/issues
Classifier: Programming Language :: Python :: 3
Classifier: License :: OSI Approved :: Apache Software License
Classifier: Operating System :: OS Independent
Requires-Python: >=3.9
License-File: LICENSE
Requires-Dist: setuptools>=61.0
Requires-Dist: opencv-python>=4.8.1.78
Requires-Dist: scipy>=1.11.3
Requires-Dist: numpy>=1.26.1
Requires-Dist: ehdg_tools>=4.6.1
Requires-Dist: pillow>=11.0.0
Requires-Dist: pymediainfo>=6.1.0
